[
  {
    "name": "Razzmatazz",
    "addrCity": "Barcelona",
    "addrStreet": "Carrer dels Almogàvers",
    "addrHouseNumber": "122",
    "addrpostcode": "08018",
    "website": "https://www.salarazzmatazz.com",
    "instagram": "https://www.instagram.com/salarazzmatazz",
    "facebook": "https://www.facebook.com/RazzmatazzBarcelona",
    "phone": "+34 933 20 82 00",
    "information": "Una de las discotecas más icónicas de Barcelona con múltiples salas y música variada",
    "banner": null,
    "region": "Barcelonès",
    "twitter": "https://twitter.com/razzmatazzbcn"
  },
  {
    "name": "Opium Mar",
    "addrCity": "Barcelona",
    "addrStreet": "Passeig Marítim de la Barceloneta",
    "addrHouseNumber": "34",
    "addrpostcode": "08003",
    "website": "https://opiumbarcelona.com",
    "instagram": "https://www.instagram.com/opiumbarcelona",
    "facebook": "https://www.facebook.com/OpiumBarcelona",
    "phone": "+34 932 25 81 60",
    "information": "Club de playa con fiestas internacionales y DJs de renombre",
    "banner": null,
    "region": "Barcelonès",
    "twitter": null
  },
  {
    "name": "Sala Apolo",
    "addrCity": "Barcelona",
    "addrStreet": "Carrer Nou de la Rambla",
    "addrHouseNumber": "113",
    "addrpostcode": "08004",
    "website": "https://www.sala-apolo.com",
    "instagram": "https://www.instagram.com/salaapolo",
    "facebook": "https://www.facebook.com/salaapolo",
    "phone": "+34 934 41 40 01",
    "information": "Club histórico con programación ecléctica y conciertos en vivo",
    "banner": null,
    "region": "Barcelonès",
    "twitter": "https://twitter.com/salaapolo"
  },
  {
    "name": "Pacha Barcelona",
    "addrCity": "Barcelona",
    "addrStreet": "Carrer dels Almogàvers",
    "addrHouseNumber": "122",
    "addrpostcode": "08018",
    "website": "https://www.pachabarcelona.com",
    "instagram": "https://www.instagram.com/pachabarcelona",
    "facebook": "https://www.facebook.com/PachaBarcelonaOfficial",
    "phone": "+34 932 25 19 00",
    "information": "Franchise del famoso club ibicenco con ambiente exclusivo",
    "banner": null,
    "region": "Barcelonès",
    "twitter": null
  },
  {
    "name": "Moog",
    "addrCity": "Barcelona",
    "addrStreet": "Carrer de l'Arc del Teatre",
    "addrHouseNumber": "3",
    "addrpostcode": "08002",
    "website": null,
    "instagram": "https://www.instagram.com/moogbarcelona",
    "facebook": null,
    "phone": null,
    "information": "Club underground especializado en música electrónica",
    "banner": null,
    "region": "Barcelonès",
    "twitter": null
  },
  {
    "name": "Tropics",
    "addrCity": "Lloret de Mar",
    "addrStreet": "Avinguda Vila de Tossa",
    "addrHouseNumber": "27",
    "addrpostcode": "17310",
    "website": "https://www.tropics.es",
    "instagram": "https://www.instagram.com/tropicslloret",
    "facebook": "https://www.facebook.com/tropicslloret",
    "phone": "+34 972 36 73 74",
    "information": "Club de verano con piscina y ambiente tropical",
    "banner": null,
    "region": "Selva",
    "twitter": null
  },
  {
    "name": "Colossus",
    "addrCity": "Lloret de Mar",
    "addrStreet": "Carrer de Sant Carles",
    "addrHouseNumber": "16",
    "addrpostcode": "17310",
    "website": null,
    "instagram": "https://www.instagram.com/colossusnightclub",
    "facebook": null,
    "phone": null,
    "information": "Discoteca grande con varias zonas y música comercial",
    "banner": null,
    "region": "Selva",
    "twitter": null
  },

  {
    "name": "Sutton",
    "addrCity": "Barcelona",
    "addrStreet": "Carrer de Tuset",
    "addrHouseNumber": "13",
    "addrpostcode": "08006",
    "website": "https://suttonbarcelona.com",
    "instagram": "https://www.instagram.com/suttonbcn",
    "facebook": null,
    "phone": "+34 932 38 76 78",
    "information": "Club exclusivo con ambiente VIP y música comercial",
    "banner": null,
    "region": "Barcelonès",
    "twitter": null
  },
  {
    "name": "Shôko",
    "addrCity": "Barcelona",
    "addrStreet": "Passeig Marítim de la Barceloneta",
    "addrHouseNumber": "36",
    "addrpostcode": "08003",
    "website": "https://shoko.barcelona",
    "instagram": "https://www.instagram.com/shokobarcelona",
    "facebook": "https://www.facebook.com/shokobarcelona",
    "phone": "+34 932 25 92 00",
    "information": "Club de playa con restaurante y sesiones de DJs internacionales",
    "banner": null,
    "region": "Barcelonès",
    "twitter": null
  },
  {
    "name": "La Terrrazza",
    "addrCity": "Barcelona",
    "addrStreet": "Av. de Francesc Ferrer i Guàrdia",
    "addrHouseNumber": "s/n",
    "addrpostcode": "08038",
    "website": "https://latterrazza.com",
    "instagram": "https://www.instagram.com/latterrazza",
    "facebook": null,
    "phone": null,
    "information": "Club de verano en Poble Espanyol con música electrónica",
    "banner": null,
    "region": "Barcelonès",
    "twitter": null
  },
  {
    "name": "Catwalk",
    "addrCity": "Barcelona",
    "addrStreet": "Carrer de Ramon Trias Fargas",
    "addrHouseNumber": "2",
    "addrpostcode": "08005",
    "website": null,
    "instagram": "https://www.instagram.com/catwalkbarcelona",
    "facebook": null,
    "phone": null,
    "information": "Club frente al mar con fiestas temáticas",
    "banner": null,
    "region": "Barcelonès",
    "twitter": null
  },
  {
    "name": "Bling Bling",
    "addrCity": "Barcelona",
    "addrStreet": "Carrer de Sevilla",
    "addrHouseNumber": "8",
    "addrpostcode": "08001",
    "website": "https://blingblingbarcelona.com",
    "instagram": "https://www.instagram.com/blingblingbcn",
    "facebook": null,
    "phone": "+34 935 24 40 22",
    "information": "Club de lujo con decoración ostentosa y música house",
    "banner": null,
    "region": "Barcelonès",
    "twitter": null
  },
  {
    "name": "La Sala",
    "addrCity": "Tarragona",
    "addrStreet": "Carrer de les Coques",
    "addrHouseNumber": "5",
    "addrpostcode": "43003",
    "website": null,
    "instagram": "https://www.instagram.com/lasalatarragona",
    "facebook": "https://www.facebook.com/lasalatarragona",
    "phone": null,
    "information": "Discoteca histórica de Tarragona con varias plantas",
    "banner": null,
    "region": "Tarragonès",
    "twitter": null
  },
  {
    "name": "Bass",
    "addrCity": "Tarragona",
    "addrStreet": "Carrer del Gasòmetre",
    "addrHouseNumber": "16",
    "addrpostcode": "43001",
    "website": null,
    "instagram": null,
    "facebook": null,
    "phone": null,
    "information": "Club underground especializado en techno y drum & bass",
    "banner": null,
    "region": "Tarragonès",
    "twitter": null
  },
  {
    "name": "La Mònica",
    "addrCity": "Girona",
    "addrStreet": "Plaça de la Independència",
    "addrHouseNumber": "9",
    "addrpostcode": "17001",
    "website": "https://lamonica.cat",
    "instagram": "https://www.instagram.com/lamonicagirona",
    "facebook": null,
    "phone": "+34 972 22 46 61",
    "information": "Club universitario con música mainstream y sesiones en vivo",
    "banner": null,
    "region": "Gironès",
    "twitter": null
  },
  {
    "name": "Disco Century",
    "addrCity": "Lleida",
    "addrStreet": "Carrer del Riu Segre",
    "addrHouseNumber": "15",
    "addrpostcode": "25007",
    "website": null,
    "instagram": null,
    "facebook": "https://www.facebook.com/centuryclub",
    "phone": null,
    "information": "Principal club nocturno de Lleida con pista de baile iluminada",
    "banner": null,
    "region": "Segrià",
    "twitter": null
  },
  {
    "name": "Pacha Sitges",
    "addrCity": "Sitges",
    "addrStreet": "Carrer de Sant Pau",
    "addrHouseNumber": "9",
    "addrpostcode": "08870",
    "website": "https://www.pachasitges.com",
    "instagram": "https://www.instagram.com/pachasitges",
    "facebook": "https://www.facebook.com/pachasitges",
    "phone": "+34 938 11 45 66",
    "information": "Franchise del famoso club en el corazón de Sitges",
    "banner": null,
    "region": "Barcelonès",
    "twitter": null
  },
  {
    "name": "Atlantic",
    "addrCity": "Sitges",
    "addrStreet": "Carrer de Sant Bonaventura",
    "addrHouseNumber": "13",
    "addrpostcode": "08870",
    "website": null,
    "instagram": "https://www.instagram.com/atlanticsitges",
    "facebook": null,
    "phone": null,
    "information": "Club gay-friendly con drag shows y música pop",
    "banner": null,
    "region": "Barcelonès",
    "twitter": null
  },
  {
    "name": "Port Avenue",
    "addrCity": "Salou",
    "addrStreet": "Carrer de Carles Buïgas",
    "addrHouseNumber": "2",
    "addrpostcode": "43840",
    "website": "https://portavenue.com",
    "instagram": "https://www.instagram.com/portavenuesalou",
    "facebook": null,
    "phone": "+34 977 38 31 31",
    "information": "Mega-discoteca con espectáculos pirotécnicos y DJs internacionales",
    "banner": null,
    "region": "Tarragonès",
    "twitter": null
  },
  {
    "name": "Oasis",
    "addrCity": "Salou",
    "addrStreet": "Carrer de Vilafranca",
    "addrHouseNumber": "14",
    "addrpostcode": "43840",
    "website": null,
    "instagram": null,
    "facebook": "https://www.facebook.com/oasissalou",
    "phone": null,
    "information": "Club de verano con jardines y ambiente tropical",
    "banner": null,
    "region": "Tarragonès",
    "twitter": null
  },
  {
    "name": "Disco Tropics",
    "addrCity": "Blanes",
    "addrStreet": "Carrer de la Punta",
    "addrHouseNumber": "5",
    "addrpostcode": "17300",
    "website": null,
    "instagram": null,
    "facebook": null,
    "phone": null,
    "information": "Discoteca clásica de la Costa Brava con música retro",
    "banner": null,
    "region": "Selva",
    "twitter": null
  },
  {
    "name": "Maremàgnum",
    "addrCity": "Mataró",
    "addrStreet": "Passeig Marítim",
    "addrHouseNumber": "45",
    "addrpostcode": "08302",
    "website": null,
    "instagram": "https://www.instagram.com/maremagnumclub",
    "facebook": null,
    "phone": null,
    "information": "Club frente al mar con terrazas y música chill-out",
    "banner": null,
    "region": "Maresme",
    "twitter": null
  },
  {
    "name": "The Clown",
    "addrCity": "Calella",
    "addrStreet": "Carrer del Cap Negret",
    "addrHouseNumber": "10",
    "addrpostcode": "08370",
    "website": null,
    "instagram": null,
    "facebook": "https://www.facebook.com/theclowncalella",
    "phone": null,
    "information": "Discoteca emblemática con decoración circense",
    "banner": null,
    "region": "Maresme",
    "twitter": null
  },
  {
    "name": "Otto Zutz",
    "addrCity": "Barcelona",
    "addrStreet": "Carrer de Lincoln",
    "addrHouseNumber": "15",
    "addrpostcode": "08006",
    "website": "https://ottozutz.com",
    "instagram": "https://www.instagram.com/ottozutzbcn",
    "facebook": null,
    "phone": "+34 932 38 07 22",
    "information": "Club de diseño con tres plantas y música house/electrónica",
    "banner": null,
    "region": "Barcelonès",
    "twitter": null
  },
  {
    "name": "Metro Dance Club",
    "addrCity": "Reus",
    "addrStreet": "Carrer de Sant Joan",
    "addrHouseNumber": "27",
    "addrpostcode": "43201",
    "website": null,
    "instagram": "https://www.instagram.com/metrodancereus",
    "facebook": null,
    "phone": null,
    "information": "Principal club de Reus con música latina y sesiones de reggaeton",
    "banner": null,
    "region": "Baix Camp",
    "twitter": null
  },
  {
    "name": "Sala Salamandra",
    "addrCity": "Sabadell",
    "addrStreet": "Carrer de la Indústria",
    "addrHouseNumber": "45",
    "addrpostcode": "08202",
    "website": null,
    "instagram": null,
    "facebook": "https://www.facebook.com/salamandrasabadell",
    "phone": null,
    "information": "Sala versátil con conciertos y fiestas temáticas los fines de semana",
    "banner": null,
    "region": "Vallès Occidental",
    "twitter": null
  },
  {
    "name": "Club Náutico",
    "addrCity": "Amposta",
    "addrStreet": "Carrer del Moll",
    "addrHouseNumber": "s/n",
    "addrpostcode": "43870",
    "website": null,
    "instagram": "https://www.instagram.com/clubnauticoamposta",
    "facebook": null,
    "phone": null,
    "information": "Club de verano junto al Delta del Ebro con ambiente playero",
    "banner": null,
    "region": "Montsià",
    "twitter": null
  },
  {
    "name": "Myth Club",
    "addrCity": "Terrassa",
    "addrStreet": "Carrer de les Ànimes",
    "addrHouseNumber": "11",
    "addrpostcode": "08221",
    "website": null,
    "instagram": null,
    "facebook": "https://www.facebook.com/mythclubterrassa",
    "phone": null,
    "information": "Discoteca juvenil con música comercial y karaoke",
    "banner": null,
    "region": "Vallès Occidental",
    "twitter": null
  },
  {
    "name": "Chill Out Rosa",
    "addrCity": "Roses",
    "addrStreet": "Avinguda de Rhode",
    "addrHouseNumber": "78",
    "addrpostcode": "17480",
    "website": null,
    "instagram": null,
    "facebook": null,
    "phone": null,
    "information": "Club al aire libre con vistas a la bahía de Roses",
    "banner": null,
    "region": "Alt Empordà",
    "twitter": null
  },
  {
    "name": "Karma",
    "addrCity": "Figueres",
    "addrStreet": "Carrer de la Jonquera",
    "addrHouseNumber": "5",
    "addrpostcode": "17600",
    "website": null,
    "instagram": "https://www.instagram.com/karmafigueres",
    "facebook": null,
    "phone": null,
    "information": "Club pequeño con ambiente alternativo y DJs locales",
    "banner": null,
    "region": "Alt Empordà",
    "twitter": null
  },
  {
    "name": "Les carpes",
    "addrCity": "Vic",
    "addrStreet": "Carrer de Manlleu",
    "addrHouseNumber": "15",
    "addrpostcode": "08500",
    "website": null,
    "instagram": null,
    "facebook": "https://www.facebook.com/salalacarpa",
    "phone": null,
    "information": "Sala multiusos con fiestas universitarias los viernes",
    "banner": null,
    "region": "Ossona",
    "twitter": null
  },
  {
    "name": "Hype",
    "addrCity": "Vic",
    "addrStreet": "Carrer de Manlleu",
    "addrHouseNumber": "15",
    "addrpostcode": "08500",
    "website": null,
    "instagram": null,
    "facebook": "https://www.facebook.com/hypevic",
    "phone": null,
    "information": "Sala multiusos con fiestas universitarias los viernes",
    "banner": null,
    "region": "Ossona",
    "twitter": null
  },
  {
    "name": "El Celvic",
    "addrCity": "Vic",
    "addrStreet": "Carrer de Manlleu",
    "addrHouseNumber": "15",
    "addrpostcode": "08500",
    "website": null,
    "instagram": null,
    "facebook": "https://www.facebook.com/Celvic",
    "phone": null,
    "information": "",
    "banner": null,
    "region": "Ossona",
    "twitter": null
  },
  {
    "name": "Disco Tropicana",
    "addrCity": "Cambrils",
    "addrStreet": "Carrer de Vilafortuny",
    "addrHouseNumber": "34",
    "addrpostcode": "43850",
    "website": null,
    "instagram": null,
    "facebook": null,
    "phone": null,
    "information": "Discoteca de los 90 renovada con música retro los jueves",
    "banner": null,
    "region": "Baix Camp",
    "twitter": null
  },
  {
    "name": "L'Antic Teatre",
    "addrCity": "Barcelona",
    "addrStreet": "Carrer de Verdaguer i Callís",
    "addrHouseNumber": "12",
    "addrpostcode": "08003",
    "website": "https://www.anticteatre.com",
    "instagram": "https://www.instagram.com/anticteatre",
    "facebook": null,
    "phone": "+34 933 15 23 54",
    "information": "Espacio cultural con fiestas alternativas y performances",
    "banner": null,
    "region": "Barcelonès",
    "twitter": null
  },
  {
    "name": "Club 7",
    "addrCity": "Manresa",
    "addrStreet": "Carrer de Balmes",
    "addrHouseNumber": "7",
    "addrpostcode": "08241",
    "website": null,
    "instagram": null,
    "facebook": "https://www.facebook.com/club7manresa",
    "phone": null,
    "information": "Discoteca clásica con música española y sesiones de karaoke",
    "banner": null,
    "region": "Bages",
    "twitter": null
  },
  {
    "name": "La Cava",
    "addrCity": "Igualada",
    "addrStreet": "Carrer de la Font",
    "addrHouseNumber": "22",
    "addrpostcode": "08700",
    "website": null,
    "instagram": null,
    "facebook": null,
    "phone": null,
    "information": "Club subterráneo con arquitectura industrial y techno",
    "banner": null,
    "region": "Anoia",
    "twitter": null
  },
  {
    "name": "Sala Bikini",
    "addrCity": "Barcelona",
    "addrStreet": "Carrer de Deu i Mata",
    "addrHouseNumber": "105",
    "addrpostcode": "08029",
    "website": "https://www.salabikini.com",
    "instagram": "https://www.instagram.com/salabikinibcn",
    "facebook": null,
    "phone": "+34 933 22 08 00",
    "information": "Icono modernista con programación ecléctica y acústicos",
    "banner": null,
    "region": "Barcelonès",
    "twitter": null
  },
  {
    "name": "Disco Tito's",
    "addrCity": "Vilafranca del Penedès",
    "addrStreet": "Carrer de Sant Joan",
    "addrHouseNumber": "8",
    "addrpostcode": "08720",
    "website": null,
    "instagram": null,
    "facebook": "https://www.facebook.com/titosvilafranca",
    "phone": null,
    "information": "Club tradicional con orquesta en vivo los sábados",
    "banner": null,
    "region": "Alt Penedès",
    "twitter": null
  },
  {
    "name": "The Loft",
    "addrCity": "Girona",
    "addrStreet": "Carrer de la Barca",
    "addrHouseNumber": "3",
    "addrpostcode": "17004",
    "website": null,
    "instagram": "https://www.instagram.com/theloftgirona",
    "facebook": null,
    "phone": null,
    "information": "Club boutique con cócteles artesanales y soul music",
    "banner": null,
    "region": "Gironès",
    "twitter": null
  }
]
